[[{"location":"/Users/Conner/School/1st Semester/CSCI 1301/Eclipse Coding/workspace/Project 2","type":"PROJECT","hints":{}},"ABSENT"],[{"location":"/Users/Conner/School/1st Semester/CSCI 1301/Eclipse Coding/workspace/Bank Account","type":"PROJECT","hints":{}},"ABSENT"],[{"location":"/System/Library/Java/JavaVirtualMachines/1.6.0.jdk/Contents/Home","type":"JRE","hints":{"EXECUTION_ENVIRONMENT":"JavaSE-1.6"}},"jre:jre:1.6.0"],[{"location":"/Users/Conner/School/1st Semester/CSCI 1301/Eclipse Coding/workspace/Lab 3","type":"PROJECT","hints":{}},"ABSENT"],[{"location":"/Users/Conner/School/1st Semester/CSCI 1301/Eclipse Coding/workspace/Bank Account (Lab 5)","type":"PROJECT","hints":{}},"ABSENT"],[{"location":"/Users/Conner/School/1st Semester/CSCI 1301/Eclipse Coding/workspace/Representing Names","type":"PROJECT","hints":{}},"ABSENT"],[{"location":"/Users/Conner/School/1st Semester/CSCI 1301/Eclipse Coding/workspace/Band Booster","type":"PROJECT","hints":{}},"ABSENT"],[{"location":"/Users/Conner/School/1st Semester/CSCI 1301/Eclipse Coding/workspace/Rolling Dice","type":"PROJECT","hints":{}},"ABSENT"],[{"location":"/Users/Conner/School/1st Semester/CSCI 1301/Eclipse Coding/workspace/Project Three","type":"PROJECT","hints":{}},"ABSENT"]]